klv_parser/__init__.py
klv_parser/common.py
klv_parser/element.py
klv_parser/elementparser.py
klv_parser/klvparser.py
klv_parser/misb0102.py
klv_parser/misb0601.py
klv_parser/misb0903.py
klv_parser/misbEG0104.py
klv_parser/seriesparser.py
klv_parser/setparser.py
klv_parser/streamparser.py
klv_parser-0.0.5.dist-info/licenses/LICENSE.txt
klv_parser-0.0.5.dist-info/METADATA
klv_parser-0.0.5.dist-info/WHEEL
klv_parser-0.0.5.dist-info/top_level.txt
klv_parser-0.0.5.dist-info/RECORD
